sourcery.py
python_sourcery-0.1.0.dist-info/LICENSE
python_sourcery-0.1.0.dist-info/WHEEL
python_sourcery-0.1.0.dist-info/METADATA
python_sourcery-0.1.0.dist-info/RECORD
