Metadata-Version: 2.1
Name: python-sourcery
Version: 0.1.0
Summary: Sources is all you need.
License: MIT
Author: Amirouche
Author-email: amirouche@hyper.dev
Requires-Python: >=3.7,<4.0
Classifier: License :: OSI Approved :: MIT License
Classifier: Programming Language :: Python :: 3
Classifier: Programming Language :: Python :: 3.7
Classifier: Programming Language :: Python :: 3.8
Classifier: Programming Language :: Python :: 3.9
Requires-Dist: asyncio-foundationdb (>=0.10.1,<0.11.0)
Requires-Dist: httpx (>=0.18.2,<0.19.0)
Requires-Dist: loguru (>=0.5.3,<0.6.0)
Requires-Dist: ujson (>=4.0.2,<5.0.0)
